LICENSE
README.md
setup.py
iomanage/__init__.py
iomanage/iomanage.py
iomanage.egg-info/PKG-INFO
iomanage.egg-info/SOURCES.txt
iomanage.egg-info/dependency_links.txt
iomanage.egg-info/top_level.txt