Metadata-Version: 2.1
Name: iomanage
Version: 1.1.1
Summary: Manages IO operations of a single file
Home-page: https://github.com/Katistic/IOManage
Author: Katistic
License: MIT
Platform: UNKNOWN
Classifier: License :: OSI Approved :: MIT License
Classifier: Programming Language :: Python :: 3
Classifier: Programming Language :: Python :: 3.7
Classifier: Programming Language :: Python :: 3.8
